flagvault_sdk/__init__.py
flagvault_sdk/flagvault_sdk.py
flagvault_sdk-1.3.0.dist-info/licenses/LICENSE
flagvault_sdk-1.3.0.dist-info/METADATA
flagvault_sdk-1.3.0.dist-info/WHEEL
flagvault_sdk-1.3.0.dist-info/top_level.txt
flagvault_sdk-1.3.0.dist-info/RECORD
