Metadata-Version: 2.4
Name: flagvault-sdk
Version: 1.3.0
Summary: Lightweight Python SDK for FlagVault with intelligent caching, enabling seamless feature flag integration and real-time flag status checks for Python applications.
Home-page: https://github.com/flagvault/sdk-py
Author: FlagVault
Author-email: accounts@flagvault.com
Project-URL: Bug Reports, https://github.com/flagvault/sdk-py/issues
Project-URL: Source, https://github.com/flagvault/sdk-py
Project-URL: Documentation, https://flagvault.com/docs
Keywords: feature-flag,feature-flags,feature-toggle,feature-toggles,sdk,python,flagvault,remote-config,a-b-testing,experimentation,caching,performance
Classifier: Development Status :: 5 - Production/Stable
Classifier: Intended Audience :: Developers
Classifier: License :: OSI Approved :: MIT License
Classifier: Programming Language :: Python :: 3
Classifier: Programming Language :: Python :: 3.6
Classifier: Programming Language :: Python :: 3.7
Classifier: Programming Language :: Python :: 3.8
Classifier: Programming Language :: Python :: 3.9
Classifier: Programming Language :: Python :: 3.10
Classifier: Programming Language :: Python :: 3.11
Classifier: Programming Language :: Python :: 3.12
Classifier: Topic :: Software Development :: Libraries :: Python Modules
Classifier: Topic :: Internet :: WWW/HTTP
Requires-Python: >=3.6
License-File: LICENSE
Requires-Dist: requests>=2.25.0
Provides-Extra: dev
Requires-Dist: pytest>=6.0; extra == "dev"
Requires-Dist: pytest-cov>=2.10; extra == "dev"
Requires-Dist: flake8>=3.8; extra == "dev"
Requires-Dist: black>=21.0; extra == "dev"
Requires-Dist: isort>=5.0; extra == "dev"
Requires-Dist: mypy>=0.900; extra == "dev"
Dynamic: author
Dynamic: author-email
Dynamic: classifier
Dynamic: description
Dynamic: description-content-type
Dynamic: home-page
Dynamic: keywords
Dynamic: license-file
Dynamic: project-url
Dynamic: provides-extra
Dynamic: requires-dist
Dynamic: requires-python
Dynamic: summary
